ziptool/__init__.py
ziptool/fetch_data.py
ziptool/geo_conversion.py
ziptool/interface.py
ziptool/load.py
ziptool/query_by_zip.py
ziptool/resources/zip_tract_122021.parquet
ziptool/utils.py
ziptool-0.0.1.dist-info/WHEEL
ziptool-0.0.1.dist-info/METADATA
ziptool-0.0.1.dist-info/RECORD
